setup.py
EXOFUNC/EXOFUNC.py
EXOFUNC/__init__.py
EXOFUNC.egg-info/PKG-INFO
EXOFUNC.egg-info/SOURCES.txt
EXOFUNC.egg-info/dependency_links.txt
EXOFUNC.egg-info/top_level.txt